Workbook
Name members: Members!$A$2:$A$31

Sheet Statement
A1: STANFORD-LE-HOPE LODGE NO: 5217
A2: STATEMENT OF ACCOUNTS FOR THE YEAR 2025-2026 | J2: For 2026-27
N3: For 25/26 | Q3: Last Year
C4: GENERAL FUND ACCOUNTS | J4: Members will be | L4: 23 | N4: Members | O4: 27 | Q4: Members | R4: 31
A5: INCOME | C5: £ | E5: EXPENDITURE | H5: £ | J5: Initiates | L5: 2 | N5: UGLE | O5: =SUM(O6:O7)*O4 -> 2349 | Q5: UGLE | R5: =SUM(R6:R7)*R4 -> 2108
A6: Dining Fees | C6: =Bank!P98+Bank!Q98+Cash!D57 -> 3232.08 | E6: Catering | H6: =Bank!AF98 -> 3038 | J6: Total Members | L6: =SUM(L4:L5) -> 25 | N6: UGLE Dues | O6: 70 | Q6: UGLE Dues | R6: 51
A7: Subscriptions | C7: =Bank!O98+Cash!C57 -> 4369.4 | E7: UGLE | H7: =Bank!AB98 -> 2393.2 | N7: UGLE Grand Charity | O7: 17 | Q7: UGLE Charity | R7: 17
A8: Initiation Fees | C8: =Bank!R98 -> 100 | E8: PGLE | H8: =Bank!AC98 -> 556 | J8: Estimated increase in UGLE/PGL/Orsett | L8: 1.1
A9: Chapter C of I Rent | C9: =SUM(Bank!V:V) -> 422.22 | E9: Orsett Masonic Hall rent | H9: =Bank!AD98 -> 2160 | N9: PGL | O9: =SUM(O10:O11)*O4 -> 418.5 | Q9: PGL | R9: =SUM(R10:R11)*R4 -> 480.5
A10: SumUp | C10: =Bank!S98 -> 0 | E10: L of I Rent Woolmarket | H10: =Bank!AE98 -> 555 | J10: UGLE | N10: PGL Dues | O10: 12 | Q10: PGL Dues | R10: 12
E11: Tylers Fee | H11: =Cash!K57 -> 180 | J11: UGLE Dues | K11: 70 | L11: =K11*$L$8 -> 77 | N11: PGL Charity | O11: 3.5 | Q11: PGL Charity | R11: 3.5
E12: Bank Charges | H12: =Bank!AG98 -> 6 | J12: UGLE Grand Charity | K12: 17 | L12: =K12*$L$8 -> 18.7
A13: Total | C13: =SUM(C6:C12) -> 8123.7 | E13: Total | H13: =SUM(H6:H12) -> 8888.2 | J13: Total UGLE | L13: =SUM(L11:L12)*L6 -> 2392.5 | N13: Orsett | O13: =O4*O14*O15 -> 2160 | Q13: Orsett
A14: Surplus / Deficit | D14: =C13-H13 -> -764.5 | N14: Meetings | O14: 5
J15: PGL | N15: Unit price | O15: 16
A16: INCOME | C16: CHARITY ACCOUNT | E16: EXPENSES | J16: PGL Dues | K16: 12 | L16: =K16*$L$8 -> 13.2
A17: Gavels | C17: =Bank!T98+Cash!E57 -> 613.15 | E17: Relief Chest | H17: =Bank!Z98 -> 0 | J17: PGL Charity | K17: 3.5 | L17: =K17*$L$8 -> 3.85
A18: Raffles | C18: =Cash!F57 -> 385 | E18: Charity donations from Lodge Funds | H18: =Bank!AA98+Cash!I57 -> 620 | J18: Total PGL | L18: =SUM(L16:L17)*L6 -> 426.25
A19: Charity Donations | C19: =Bank!U98 -> 0
A20: Total | C20: =SUM(C17:C19) -> 998.15 | E20: Total | H20: =SUM(H17:H19) -> 620 | J20: Orsett
J21: Meetings | K21: 5 | L21: =K21*$L$8 -> 5.5
A22: INCOME | C22: BENEVOLENT FUND | E22: EXPENDITURE | J22: Unit price | K22: 16 | L22: =K22*$L$8 -> 17.6
E23: Widows Christmas gifts | H23: =Bank!AH98 -> 160 | J23: Total Orsett | L23: =SUM(L21:L22)*L6 -> 577.5
C24: =F47 -> 0 | E24: Almoner's expenses | H24: =Cash!J57 -> 7
A25: Total | C25: =SUM(C23:C24) -> 0 | E25: Total | H25: =SUM(H23:H24) -> 167
J26: Expense
J27: =E7 -> UGLE | K27: =K13 -> 0 | L27: =L13 -> 2392.5
A28: INCOME | C28: LODGE OF INSTRUCTION | E28: EXPENDITURE | J28: =E8 -> PGLE | K28: =K18 -> 0 | L28: =L18 -> 426.25
A29: Collections | C29: =Bank!W98 -> 177.3 | H29: =Bank!AH104 -> 0 | J29: =E9 -> Orsett Masonic Hall rent | K29: =K20 -> 0 | L29: =L23 -> 577.5
A30: Total | C30: =SUM(C29:C29) -> 177.3 | E30: Total | H30: =SUM(H29:H29) -> 0 | J30: =E10 -> L of I Rent Woolmarket | L30: =H10-150 -> 405
J31: =E11 -> Tylers Fee | L31: =H11 -> 180
C32: Bank Reconciliation | J32: Secretary Subs | L32: 200
A33: Current account balance 01/08/2025 | C33: 21053.72 | E33: Current account balance 31/07/2026 | H33: =Bank!F96 -> 20732.67 | J33: Vip Meals | L33: 90
A34: Plus receipts | C34: =SUM(Bank!D3:D96) -> 9167.15 | J34: Misc | L34: 200
A35: Less payments | C35: =SUM(Bank!E3:E96) -> 9488.2 | J35: Total | L35: =SUM(L27:L34) -> 4471.25
A36: Total | C36: =C33+C34-C35 -> 20732.67
J37: New Subs will need to be from next year | L37: =L35/L6 -> 178.85
C39: BALANCE SHEET
A40: ACCOUNT | C40: OPENING | D40: INCOME | E40: EXPENSE | F40: XFR IN | G40: XFR OUT | H40: CLOSING
A41: MAIN ACCOUNT | C41: 5141.17 | D41: =C13 -> 8123.7 | E41: =H13 -> 8888.2 | F41: =G45+G46 -> 82 | H41: =C41+D41-E41+F41-G41 -> 4458.67
A42: CHARITY ACCOUNT | C42: 744.46 | D42: =C20 -> 998.15 | E42: =H20 -> 620 | H42: =C42+D42-E42+F42-G42 -> 1122.61
A43: GLASGOW/FRANK | C43: 10689.79 | D43: 0 | E43: 0 | G43: 5000 | H43: =C43+D43-E43+F43-G43 -> 5689.79
A44: Lodge of Instruction | C44: 335.65 | D44: =Bank!W98 -> 177.3 | E44: =H30 -> 0 | H44: =C44+D44-E44+F44-G44 -> 512.95
A45: Pre-Paid Subs | C45: 127.745 | D45: =SUM(Bank!M98) -> 25 | G45: =SUM(Members!C3:C31) -> 50.6 | H45: =C45+D45-E45+F45-G45 -> 102.145
A46: Pre-Paid Dining | C46: 72.255 | D46: =Bank!N98 -> 30 | G46: =SUM(Members!D3:D31) -> 31.4 | H46: =C46+D46-E46+F46-G46 -> 70.855
A47: BENEVOLENT FUND | C47: 772.17 | E47: =H25 -> 167 | H47: =C47+D47-E47+F47-G47 -> 605.17
A48: CENTENARY FUND | C48: 3170.48 | E48: 0 | F48: 5000 | H48: =C48+D48-E48+F48-G48 -> 8170.48
C49: =SUM(C41:C48) -> 21053.72 | D49: =SUM(D41:D48) -> 9354.15 | E49: =SUM(E41:E48) -> 9675.2 | F49: =SUM(F41:F48) -> 5082 | G49: =SUM(G41:G48) -> 5082 | H49: =C49+D49-E49+F49-G49 -> 20732.67
A50: Notes
A51: =_xlfn.CONCAT(TEXT(COUNTIF(Members!G2:G31,">0"),"##")," members are in arrears (includes resigned and deceased) totalling",TEXT(Members!G32," #,###")) -> 7 members are in arrears (includes resigned and deceased) totalling 1,340
A52: The Lodge currently holds shares to the value of £733 in Orsett Masonic Hall Ltd
C54: TREASURERS REPORT
I55: =H49-H33 -> 0
A56: DINING Our dining account is running behind again, as our FULL members are paying less than the price of the meal. OPERATING COSTS Our operating costs also took a hit this year due to arrears, resignations with unpaid dues and losing one member to the Grand Lodge above.
B71: Treasurer | F71: Date
C72: W Bro S. Stock
B75: Auditor | F75: Auditor
C76: W Bro Will Fulford | G76: W Bro M Walden

Sheet Cash
A1: SEPTEMBER MEETING
A2: Item | B2: Name | C2: Subs | D2: Dining | E2: Gavel | F2: Raffle | G2: Copper Pot | H2: IN | I2: Donations | J2: Almoner | K2: Tyler | L2: OUT
A3: Member | B3: Stribling,Martyn | D3: 30 | H3: =SUM(C3:G3) -> 30 | L3: =SUM(I3:K3) -> 0
A4: Member | B4: Croucher, Alan | D4: 30 | H4: =SUM(C4:G4) -> 30 | L4: =SUM(I4:K4) -> 0
A5: Tyler | B5: Keith Purcell | H5: =SUM(C5:G5) -> 0 | K5: 45 | L5: =SUM(I5:K5) -> 45 | M5: =SUM(H3:H5)-SUM(L3:L5) -> 15
A6: Collection | B6: Gavel | E6: 95 | H6: =SUM(C6:G6) -> 95 | L6: =SUM(I6:K6) -> 0 | M6: =H6-L6 -> 95
A7: Collection | B7: Raffle | F7: 155 | H7: =SUM(C7:G7) -> 155 | L7: =SUM(I7:K7) -> 0 | M7: =H7-L7 -> 155
A8: NOVEMBER MEETING | H8: =SUM(C8:G8) -> 0
A9: Item | B9: Name | C9: Subs | D9: Dining | E9: Gavel | F9: Raffle | G9: Copper Pot | H9: IN | I9: Donations | J9: Almoner | K9: Tyler | L9: OUT
A10: Member | B10: Withey, Graham | D10: 30 | H10: =SUM(C10:G10) -> 30 | L10: =SUM(I10:K10) -> 0
A11: Member | B11: James,Ian | D11: 30 | H11: =SUM(C11:G11) -> 30 | L11: =SUM(I11:K11) -> 0
A12: Member | B12: Stribling,Martyn | D12: 30 | H12: =SUM(C12:G12) -> 30 | L12: =SUM(I12:K12) -> 0
A13: Member | B13: Chipperfield,David | D13: 30 | H13: =SUM(C13:G13) -> 30 | L13: =SUM(I13:K13) -> 0
A14: *Visitor | B14: Guest of Andrew | D14: 30 | H14: =SUM(C14:G14) -> 30 | L14: =SUM(I14:K14) -> 0
A15: *Visitor | B15: Guest of Nick | D15: 30 | H15: =SUM(C15:G15) -> 30 | L15: =SUM(I15:K15) -> 0
A16: *Visitor | B16: Guest of Keith | D16: 30 | H16: =SUM(C16:G16) -> 30 | L16: =SUM(I16:K16) -> 0
A17: *Visitor | B17: Guest of Keith | D17: 30 | H17: =SUM(C17:G17) -> 30 | L17: =SUM(I17:K17) -> 0
A18: *Visitor | B18: Guest of Peter | H18: =SUM(C18:G18) -> 0 | L18: =SUM(I18:K18) -> 0
A19: Expenses | B19: Peter Moss | H19: =SUM(C19:G19) -> 0 | J19: 7 | L19: =SUM(I19:K19) -> 7
A20: Tyler | B20: Keith Purcell | H20: =SUM(C20:G20) -> 0 | K20: 45 | L20: =SUM(I20:K20) -> 45 | M20: =SUM(H10:H20)-SUM(L10:L20) -> 188
A21: Collection | B21: Gavel | E21: 165 | H21: =SUM(C21:G21) -> 165 | L21: =SUM(I21:K21) -> 0 | M21: =H21-L21 -> 165
A22: Collection | B22: Raffle | H22: =SUM(C22:G22) -> 0 | L22: =SUM(I22:K22) -> 0 | M22: =H22-L22 -> 0
A23: JANUARY MEETING
A24: Item | B24: Name | C24: Subs | D24: Dining | E24: Gavel | F24: Raffle | G24: Copper Pot | H24: IN | I24: Donations | J24: Almoner | K24: Tyler | L24: OUT
A25: Member | B25: James,Ian | D25: 30 | H25: =SUM(C25:G25) -> 30 | L25: =SUM(I25:K25) -> 0
A26: *Visitor | B26: D.Bailey | D26: 30 | H26: =SUM(C26:G26) -> 30 | L26: =SUM(I26:K26) -> 0
A27: Member | B27: A.Croucher | D27: 30 | H27: =SUM(C27:G27) -> 30 | L27: =SUM(I27:K27) -> 0
A28: *Visitor | B28: A.Court | D28: 30 | H28: =SUM(C28:G28) -> 30 | L28: =SUM(I28:K28) -> 0
A29: *Visitor | B29: A.Macdonalds | D29: 30 | H29: =SUM(C29:G29) -> 30 | L29: =SUM(I29:K29) -> 0
A30: *Visitor | B30: C.Aiden | D30: 30 | H30: =SUM(C30:G30) -> 30 | L30: =SUM(I30:K30) -> 0
A31: *Visitor | B31: Lee Taylor | D31: 30 | H31: =SUM(C31:G31) -> 30 | L31: =SUM(I31:K31) -> 0
A32: Tyler | B32: Keith Purcell | H32: =SUM(C32:G32) -> 0 | K32: 45 | L32: =SUM(I32:K32) -> 45 | M32: =SUM(H25:H32)-SUM(L25:L32) -> 165
A33: Collection | B33: Gavel | E33: 195 | H33: =SUM(C33:G33) -> 195 | L33: =SUM(I33:K33) -> 0 | M33: =H33-L33 -> 195
A34: Collection | B34: Raffle | H34: =SUM(C34:G34) -> 0 | L34: =SUM(I34:K34) -> 0 | M34: =H34-L34 -> 0
A35: MARCH MEETING
A36: Item | B36: Name | C36: Subs | D36: Dining | E36: Gavel | F36: Raffle | G36: Copper Pot | H36: IN | I36: Donations | J36: Almoner | K36: Tyler | L36: OUT
A37: Member | B37: Moss,Peter | D37: -35 | H37: =SUM(C37:G37) -> -35 | L37: =SUM(I37:K37) -> 0
A38: Member | B38: Coleridge-Humphries,Connor | D38: 30 | H38: =SUM(C38:G38) -> 30 | L38: =SUM(I38:K38) -> 0
A39: Member | B39: James,Ian | D39: 30 | H39: =SUM(C39:G39) -> 30 | L39: =SUM(I39:K39) -> 0
A40: *Visitor | B40: Adrian Court | D40: 30 | H40: =SUM(C40:G40) -> 30 | L40: =SUM(I40:K40) -> 0
A41: *Visitor | B41: Clive Reeves | D41: 30 | H41: =SUM(C41:G41) -> 30 | L41: =SUM(I41:K41) -> 0
A42: Tyler | B42: Keith Purcell | H42: =SUM(C42:G42) -> 0 | K42: 45 | L42: =SUM(I42:K42) -> 45 | M42: =SUM(H37:H42)-SUM(L37:L42) -> 40
A43: Member | B43: James,Ian | C43: 100 | H43: =SUM(C43:G43) -> 100 | L43: =SUM(I43:K43) -> 0 | M43: =H43-L43 -> 100
A44: Collection | B44: Gavel | E44: 158.15 | H44: =SUM(C44:G44) -> 158.15 | L44: =SUM(I44:K44) -> 0 | M44: =H44-L44 -> 158.15
A45: Collection | B45: Raffle | F45: 230 | H45: =SUM(C45:G45) -> 230 | L45: =SUM(I45:K45) -> 0 | M45: =H45-L45 -> 230
A46: MAY MEETING
A47: Item | B47: Name | C47: Subs | D47: Dining | E47: Gavel | F47: Raffle | G47: Copper Pot | H47: IN | I47: Donations | J47: Almoner | K47: Tyler | L47: OUT
A48: Member | B48: Withey, Graham | H48: =SUM(C48:G48) -> 0 | L48: =SUM(I48:K48) -> 0
A49: Member | B49: James,Ian | H49: =SUM(C49:G49) -> 0 | L49: =SUM(I49:K49) -> 0
A50: Member | B50: Stribling,Martyn | H50: =SUM(C50:G50) -> 0 | L50: =SUM(I50:K50) -> 0
A51: *Visitor | B51: Guest | H51: =SUM(C51:G51) -> 0 | L51: =SUM(I51:K51) -> 0
A52: *Visitor | B52: Guest | H52: =SUM(C52:G52) -> 0 | L52: =SUM(I52:K52) -> 0
A53: Tyler | B53: Keith Purcell | H53: =SUM(C53:G53) -> 0 | L53: =SUM(I53:K53) -> 0 | M53: =SUM(H48:H53)-SUM(L48:L53) -> 0
A54: Collection | B54: Gavel | H54: =SUM(C54:G54) -> 0 | L54: =SUM(I54:K54) -> 0 | M54: =H54-L54 -> 0
A55: Collection | B55: Raffle | H55: =SUM(C55:G55) -> 0 | L55: =SUM(I55:K55) -> 0 | M55: =H55-L55 -> 0
A57: TOTALS | C57: =SUM(C3:C56) -> 100 | D57: =SUM(D3:D56) -> 595 | E57: =SUM(E3:E56) -> 613.15 | F57: =SUM(F3:F56) -> 385 | G57: =SUM(G3:G56) -> 0 | H57: =SUM(H3:H56) -> 1693.15 | I57: =SUM(I3:I56) -> 0 | J57: =SUM(J3:J56) -> 7 | ... M57: =SUM(M3:M56) -> 1506.15

Sheet Bank
A1: Date | B1: Details | C1: Transaction Type | D1: In | E1: Out | F1: Balance | H1: Cross-Check | J1: Cross-Check | L1: Cash | M1: Pre-Subs | N1: Pre-Dining | O1: Subs | P1: Dining | Q1: Visitor | R1: Initiation | S1: SumUp | T1: Gavel | U1: Donations | V1: Chapter LOI | W1: LOI | X1: Total | Z1: Relief | AA1: Donations | AB1: UGLE | AC1: PGLE | AD1: Orsett | AE1: WoolMkt | AF1: Caterer | AG1: Bank Charges | AH1: Widows | AI1: Total
A2: 45504 | B2: Opening Balance | C2: Opening | F2: 21053.72 | H2: =D2-X2 -> 0 | J2: =E2-AI2 -> 0 | X2: =SUM(L2:W2) -> 0 | AI2: =SUM(Z2:AH2) -> 0
A3: 45897 | B3: WALDEN M VA Mark Walden Subs | C3: Inward Payment | D3: 325 | F3: =F2+D3-E3 -> 21378.72 | H3: =D3-X3 -> 0 | J3: =E3-AI3 -> 0 | O3: 200 | P3: 125 | X3: =SUM(L3:W3) -> 325 | AI3: =SUM(Z3:AH3) -> 0
A4: 45897 | B4: CHIPPERFIELD D CHIPSLODGEPAYMENTS | C4: Inward Payment | D4: 200 | F4: =F3+D4-E4 -> 21578.72 | H4: =D4-X4 -> 0 | J4: =E4-AI4 -> 0 | O4: 200 | X4: =SUM(L4:W4) -> 200 | AI4: =SUM(Z4:AH4) -> 0
A5: 45897 | B5: MR S STOCk | C5: Inward Payment | D5: 325 | F5: =F4+D5-E5 -> 21903.72 | H5: =D5-X5 -> 0 | J5: =E5-AI5 -> 0 | O5: 200 | P5: 125 | X5: =SUM(L5:W5) -> 325 | AI5: =SUM(Z5:AH5) -> 0
A6: 45898 | B6: John Porter Arrears from 2024/25 | C6: Inward Payment | D6: 325 | F6: =F5+D6-E6 -> 22228.72 | H6: =D6-X6 -> 0 | J6: =E6-AI6 -> 0 | O6: 200 | P6: 125 | X6: =SUM(L6:W6) -> 325 | AI6: =SUM(Z6:AH6) -> 0
A7: 45898 | B7: UGLE | C7: Outward Payment | E7: 2393.2 | F7: =F6+D7-E7 -> 19835.52 | H7: =D7-X7 -> 0 | J7: =E7-AI7 -> 0 | X7: =SUM(L7:W7) -> 0 | AB7: 2393.2 | AI7: =SUM(Z7:AH7) -> 2393.2
A8: 45898 | B8: PGLE | C8: Outward Payment | E8: 556 | F8: =F7+D8-E8 -> 19279.52 | H8: =D8-X8 -> 0 | J8: =E8-AI8 -> 0 | X8: =SUM(L8:W8) -> 0 | AC8: 556 | AI8: =SUM(Z8:AH8) -> 556
A9: 45898 | B9: Connor Waldon | C9: Inward Payment | D9: 325 | F9: =F8+D9-E9 -> 19604.52 | H9: =D9-X9 -> 0 | J9: =E9-AI9 -> 0 | O9: 200 | P9: 125 | X9: =SUM(L9:W9) -> 325 | AI9: =SUM(Z9:AH9) -> 0
A10: 45898 | B10: Alan Featherstone | C10: Inward Payment | D10: 200 | F10: =F9+D10-E10 -> 19804.52 | H10: =D10-X10 -> 0 | J10: =E10-AI10 -> 0 | O10: 200 | X10: =SUM(L10:W10) -> 200 | AI10: =SUM(Z10:AH10) -> 0
A11: 45898 | B11: Will Fulford | C11: Inward Payment | D11: 325 | F11: =F10+D11-E11 -> 20129.52 | H11: =D11-X11 -> 0 | J11: =E11-AI11 -> 0 | O11: 200 | P11: 125 | X11: =SUM(L11:W11) -> 325 | AI11: =SUM(Z11:AH11) -> 0
A12: 45898 | B12: Higgins | D12: 325 | F12: =F11+D12-E12 -> 20454.52 | H12: =D12-X12 -> 0 | J12: =E12-AI12 -> 0 | O12: 200 | P12: 125 | X12: =SUM(L12:W12) -> 325 | AI12: =SUM(Z12:AH12) -> 0
A13: 45902 | B13: STOCK S + DT WITHEY SUBS | C13: Inward Payment | D13: 325 | F13: =F12+D13-E13 -> 20779.52 | H13: =D13-X13 -> 0 | J13: =E13-AI13 -> 0 | O13: 200 | P13: 125 | X13: =SUM(L13:W13) -> 325 | AI13: =SUM(Z13:AH13) -> 0
A14: 45904 | B14: THE WOOLMARKET SLH Lodge | C14: Outward Faster Payment | E14: 555 | F14: =F13+D14-E14 -> 20224.52 | H14: =D14-X14 -> 0 | J14: =E14-AI14 -> 0 | X14: =SUM(L14:W14) -> 0 | AE14: 555 | AI14: =SUM(Z14:AH14) -> 555
A15: 45904 | B15: AWCOCK D+G D A AWCOCK SUBS | C15: Inward Payment | D15: 325 | F15: =F14+D15-E15 -> 20549.52 | H15: =D15-X15 -> 0 | J15: =E15-AI15 -> 0 | O15: 200 | P15: 125 | X15: =SUM(L15:W15) -> 325 | AI15: =SUM(Z15:AH15) -> 0
A16: 45905 | B16: Raymond Mullender LODGE FEES RAY M | C16: Inward Payment | D16: 200 | F16: =F15+D16-E16 -> 20749.52 | H16: =D16-X16 -> 0 | J16: =E16-AI16 -> 0 | O16: 200 | X16: =SUM(L16:W16) -> 200 | AI16: =SUM(Z16:AH16) -> 0
A17: 45909 | B17: Raymond Mullender LODGE DINE RAY M | C17: Inward Payment | D17: 30 | F17: =F16+D17-E17 -> 20779.52 | H17: =D17-X17 -> 0 | J17: =E17-AI17 -> 0 | P17: 30 | X17: =SUM(L17:W17) -> 30 | AI17: =SUM(Z17:AH17) -> 0
A18: 45909 | B18: M Jess LODGE FEE 2025 | C18: Inward Payment | D18: 325 | F18: =F17+D18-E18 -> 21104.52 | H18: =D18-X18 -> 0 | J18: =E18-AI18 -> 0 | O18: 200 | P18: 125 | X18: =SUM(L18:W18) -> 325 | AI18: =SUM(Z18:AH18) -> 0
A19: 45912 | B19: CHIPPERFIELD D CHIPSLODGEPAYMENTS | C19: Inward Payment | D19: 30 | F19: =F18+D19-E19 -> 21134.52 | H19: =D19-X19 -> 0 | J19: =E19-AI19 -> 0 | Q19: 30 | X19: =SUM(L19:W19) -> 30 | AI19: =SUM(Z19:AH19) -> 0
A20: 45912 | B20: STEVEN PEACOCK PEACOCK | C20: Inward Payment | D20: 325 | F20: =F19+D20-E20 -> 21459.52 | H20: =D20-X20 -> 0 | J20: =E20-AI20 -> 0 | O20: 200 | P20: 125 | X20: =SUM(L20:W20) -> 325 | AI20: =SUM(Z20:AH20) -> 0
A21: 45919 | B21: STOCK S + DT 2025-SEP-DINTYL | C21: Inward Payment | D21: 15 | F21: =F20+D21-E21 -> 21474.52 | H21: =D21-X21 -> 0 | J21: =E21-AI21 -> 0 | L21: 15 | X21: =SUM(L21:W21) -> 15 | AI21: =SUM(Z21:AH21) -> 0
A22: 45919 | B22: STOCK S + DT 2025-SEP-GAVEL | C22: Inward Payment | D22: 95 | F22: =F21+D22-E22 -> 21569.52 | H22: =D22-X22 -> 0 | J22: =E22-AI22 -> 0 | L22: 95 | X22: =SUM(L22:W22) -> 95 | AI22: =SUM(Z22:AH22) -> 0
A23: 45919 | B23: AFORDERBLE CATERING SLH LODGE 5217 | C23: Outward Faster Payment | E23: 624 | F23: =F22+D23-E23 -> 20945.52 | H23: =D23-X23 -> 0 | J23: =E23-AI23 -> 0 | X23: =SUM(L23:W23) -> 0 | AF23: 624 | AI23: =SUM(Z23:AH23) -> 624
A24: 45919 | B24: STOCK S + DT 2025-SEP RAFFFLE | C24: Inward Payment | D24: 155 | F24: =F23+D24-E24 -> 21100.52 | H24: =D24-X24 -> 0 | J24: =E24-AI24 -> 0 | L24: 155 | X24: =SUM(L24:W24) -> 155 | AI24: =SUM(Z24:AH24) -> 0
A25: 45919 | B25: COLERIDGE-HUMPHR FEES | C25: Inward Payment | D25: 350 | F25: =F24+D25-E25 -> 21450.52 | H25: =D25-X25 -> 0 | J25: =E25-AI25 -> 0 | M25: 25 | O25: 200 | P25: 125 | X25: =SUM(L25:W25) -> 350 | AI25: =SUM(Z25:AH25) -> 0
A26: 45919 | B26: KASTHURI R Kasthuri ( Dining) | C26: Inward Payment | D26: 30 | F26: =F25+D26-E26 -> 21480.52 | H26: =D26-X26 -> 0 | J26: =E26-AI26 -> 0 | P26: 30 | X26: =SUM(L26:W26) -> 30 | AI26: =SUM(Z26:AH26) -> 0
A27: 45922 | B27: SumUp Payments Account MV4 PID938671 | C27: Inward Payment | D27: 88.48 | F27: =F26+D27-E27 -> 21569 | H27: =D27-X27 -> 0 | J27: =E27-AI27 -> 0 | P27: 88.48 | X27: =SUM(L27:W27) -> 88.48 | AI27: =SUM(Z27:AH27) -> 0
A28: 45922 | B28: MARSHALL ARTHUR MARSHALL JEANETTE ARTHUR MARSHALL | C28: Inward Payment | D28: 200 | F28: =F27+D28-E28 -> 21769 | H28: =D28-X28 -> 0 | J28: =E28-AI28 -> 0 | O28: 200 | X28: =SUM(L28:W28) -> 200 | AI28: =SUM(Z28:AH28) -> 0
A29: 45938 | B29: AWCOCK D LOFI 7TH OCT GAVEL | C29: Inward Payment | D29: 10 | F29: =F28+D29-E29 -> 21779 | H29: =D29-X29 -> 0 | J29: =E29-AI29 -> 0 | W29: 10 | X29: =SUM(L29:W29) -> 10 | AI29: =SUM(Z29:AH29) -> 0
A30: 45944 | B30: STRIBLING ML M Stribling | C30: Inward Payment | D30: 200 | F30: =F29+D30-E30 -> 21979 | H30: =D30-X30 -> 0 | J30: =E30-AI30 -> 0 | O30: 200 | X30: =SUM(L30:W30) -> 200 | AI30: =SUM(Z30:AH30) -> 0
A31: 45945 | B31: Ashley Coleridge IAN JAMES | C31: Inward Payment | D31: 200 | F31: =F30+D31-E31 -> 22179 | H31: =D31-X31 -> 0 | J31: =E31-AI31 -> 0 | O31: 200 | X31: =SUM(L31:W31) -> 200 | AI31: =SUM(Z31:AH31) -> 0
A32: 45945 | B32: O BRIEN KDJI OBRIEN SUBS | C32: Inward Payment | D32: 325 | F32: =F31+D32-E32 -> 22504 | H32: =D32-X32 -> 0 | J32: =E32-AI32 -> 0 | O32: 200 | P32: 125 | X32: =SUM(L32:W32) -> 325 | AI32: =SUM(Z32:AH32) -> 0
A33: 45954 | B33: AWCOCK D+G C OF I RENT 2 YRS | C33: Inward Payment | D33: 300 | F33: =F32+D33-E33 -> 22804 | H33: =D33-X33 -> 0 | J33: =E33-AI33 -> 0 | V33: 300 | X33: =SUM(L33:W33) -> 300 | AI33: =SUM(Z33:AH33) -> 0
A34: 45954 | B34: AWCOCK D S JOYCE DINING NOV | C34: Inward Payment | D34: 30 | F34: =F33+D34-E34 -> 22834 | H34: =D34-X34 -> 0 | J34: =E34-AI34 -> 0 | P34: 30 | X34: =SUM(L34:W34) -> 30 | AI34: =SUM(Z34:AH34) -> 0
A35: 45959 | B35: Raymond Mullender LODGE DINE RAY M | C35: Inward Payment | D35: 30 | F35: =F34+D35-E35 -> 22864 | H35: =D35-X35 -> 0 | J35: =E35-AI35 -> 0 | P35: 30 | X35: =SUM(L35:W35) -> 30 | AI35: =SUM(Z35:AH35) -> 0
A36: 45959 | B36: PETER MORRIS P Morris dining | C36: Inward Payment | D36: 30 | F36: =F35+D36-E36 -> 22894 | H36: =D36-X36 -> 0 | J36: =E36-AI36 -> 0 | P36: 30 | X36: =SUM(L36:W36) -> 30 | AI36: =SUM(Z36:AH36) -> 0
A37: 45965 | B37: Ashley Coleridge LOI | C37: Inward Payment | D37: 120 | F37: =F36+D37-E37 -> 23014 | H37: =D37-X37 -> 0 | J37: =E37-AI37 -> 0 | W37: 120 | X37: =SUM(L37:W37) -> 120 | AI37: =SUM(Z37:AH37) -> 0
A38: 45968 | B38: Nicholas HIGGINS Nick Higgins | C38: Inward Payment | D38: 30 | F38: =F37+D38-E38 -> 23044 | H38: =D38-X38 -> 0 | J38: =E38-AI38 -> 0 | P38: 30 | X38: =SUM(L38:W38) -> 30 | AI38: =SUM(Z38:AH38) -> 0
A39: 45971 | B39: DARREN BARTLETT Bartlett dining | C39: Inward Payment | D39: 30 | F39: =F38+D39-E39 -> 23074 | H39: =D39-X39 -> 0 | J39: =E39-AI39 -> 0 | P39: 30 | X39: =SUM(L39:W39) -> 30 | AI39: =SUM(Z39:AH39) -> 0
A40: 45975 | B40: AFORDERBLE CATERING SLH LODGE 5217 | C40: Outward Faster Payment | E40: 806 | F40: =F39+D40-E40 -> 22268 | H40: =D40-X40 -> 0 | J40: =E40-AI40 -> 0 | X40: =SUM(L40:W40) -> 0 | AF40: 806 | AI40: =SUM(Z40:AH40) -> 806
A41: 45981 | B41: STOCK S + DT NOV-DIN-TYL-ALM | C41: Inward Payment | D41: 188 | F41: =F40+D41-E41 -> 22456 | H41: =D41-X41 -> 0 | J41: =E41-AI41 -> 0 | L41: 188 | X41: =SUM(L41:W41) -> 188 | AI41: =SUM(Z41:AH41) -> 0
A42: 45982 | B42: STOCK S + DT NOV-GAVEL | C42: Inward Payment | D42: 165 | F42: =F41+D42-E42 -> 22621 | H42: =D42-X42 -> 0 | J42: =E42-AI42 -> 0 | L42: 165 | X42: =SUM(L42:W42) -> 165 | AI42: =SUM(Z42:AH42) -> 0
A43: 45986 | B43: AWCOCK D LOI 25TH NOV GAVEL | C43: Inward Payment | D43: 16.52 | F43: =F42+D43-E43 -> 22637.52 | H43: =D43-X43 -> 0 | J43: =E43-AI43 -> 0 | W43: 16.52 | X43: =SUM(L43:W43) -> 16.52 | AI43: =SUM(Z43:AH43) -> 0
A44: 45994 | B44: AWCOCK D LOI 2ND DEC GAVEL | C44: Inward Payment | D44: 8.92 | F44: =F43+D44-E44 -> 22646.44 | H44: =D44-X44 -> 0 | J44: =E44-AI44 -> 0 | W44: 8.92 | X44: =SUM(L44:W44) -> 8.92 | AI44: =SUM(Z44:AH44) -> 0
A45: 46003 | B45: M Jess dinning guest Neil | C45: Inward Payment | D45: 30 | F45: =F44+D45-E45 -> 22676.44 | H45: =D45-X45 -> 0 | J45: =E45-AI45 -> 0 | P45: 30 | X45: =SUM(L45:W45) -> 30 | AI45: =SUM(Z45:AH45) -> 0
A46: 46010 | B46: STEVEN PEACOCK PEACOCK | C46: Inward Payment | D46: 30 | F46: =F45+D46-E46 -> 22706.44 | H46: =D46-X46 -> 0 | J46: =E46-AI46 -> 0 | N46: 30 | X46: =SUM(L46:W46) -> 30 | AI46: =SUM(Z46:AH46) -> 0
A47: 46010 | B47: 800034 | C47: Cheque | E47: 40 | F47: =F46+D47-E47 -> 22666.44 | H47: =D47-X47 -> 0 | J47: =E47-AI47 -> 0 | X47: =SUM(L47:W47) -> 0 | AH47: 40 | AI47: =SUM(Z47:AH47) -> 40
A48: 46014 | B48: THOMS CH THOMS | C48: Inward Payment | D48: 30 | F48: =F47+D48-E48 -> 22696.44 | H48: =D48-X48 -> 0 | J48: =E48-AI48 -> 0 | P48: 30 | X48: =SUM(L48:W48) -> 30 | AI48: =SUM(Z48:AH48) -> 0
A49: 46014 | B49: 800030 | C49: Cheque | E49: 137 | F49: =F48+D49-E49 -> 22559.44 | H49: =D49-X49 -> 0 | J49: =E49-AI49 -> 0 | X49: =SUM(L49:W49) -> 0 | AA49: 137 | AI49: =SUM(Z49:AH49) -> 137
A50: 46014 | B50: 800029 | C50: Cheque | E50: 68 | F50: =F49+D50-E50 -> 22491.44 | H50: =D50-X50 -> 0 | J50: =E50-AI50 -> 0 | X50: =SUM(L50:W50) -> 0 | AA50: 68 | AI50: =SUM(Z50:AH50) -> 68
A51: 46020 | B51: 800031 | C51: Cheque | E51: 40 | F51: =F50+D51-E51 -> 22451.44 | H51: =D51-X51 -> 0 | J51: =E51-AI51 -> 0 | X51: =SUM(L51:W51) -> 0 | AH51: 40 | AI51: =SUM(Z51:AH51) -> 40
A52: 46022 | B52: STRIBLING ML M Stribling | C52: Inward Payment | D52: 30 | F52: =F51+D52-E52 -> 22481.44 | H52: =D52-X52 -> 0 | J52: =E52-AI52 -> 0 | P52: 30 | X52: =SUM(L52:W52) -> 30 | AI52: =SUM(Z52:AH52) -> 0
A53: 46024 | B53: M Gillam Mark Gillam | C53: Inward Payment | D53: 200 | F53: =F52+D53-E53 -> 22681.44 | H53: =D53-X53 -> 0 | J53: =E53-AI53 -> 0 | O53: 200 | X53: =SUM(L53:W53) -> 200 | AI53: =SUM(Z53:AH53) -> 0
A54: 46024 | B54: STOCK S + DT JAN GAVEL | C54: Inward Payment | D54: 195 | F54: =F53+D54-E54 -> 22876.44 | H54: =D54-X54 -> 0 | J54: =E54-AI54 -> 0 | L54: 195 | X54: =SUM(L54:W54) -> 195 | AI54: =SUM(Z54:AH54) -> 0
A55: 46024 | B55: STOCK S + DT JAN DIN-TYLER | C55: Inward Payment | D55: 165 | F55: =F54+D55-E55 -> 23041.44 | H55: =D55-X55 -> 0 | J55: =E55-AI55 -> 0 | L55: 165 | X55: =SUM(L55:W55) -> 165 | AI55: =SUM(Z55:AH55) -> 0
A56: 46024 | B56: AFORDERBLE CATERING SLH LODGE 5217 | C56: Outward Faster Payment | E56: 754 | F56: =F55+D56-E56 -> 22287.44 | H56: =D56-X56 -> 0 | J56: =E56-AI56 -> 0 | X56: =SUM(L56:W56) -> 0 | AF56: 754 | AI56: =SUM(Z56:AH56) -> 754
A57: 46024 | B57: WOODS PD P.D.WOODS | C57: Inward Payment | D57: 30 | F57: =F56+D57-E57 -> 22317.44 | H57: =D57-X57 -> 0 | J57: =E57-AI57 -> 0 | P57: 30 | X57: =SUM(L57:W57) -> 30 | AI57: =SUM(Z57:AH57) -> 0
A58: 46024 | B58: Bradley Brown Bradley Brown | C58: Inward Payment | D58: 295 | F58: =F57+D58-E58 -> 22612.44 | H58: =D58-X58 -> 0 | J58: =E58-AI58 -> 0 | O58: =200/5*3 -> 120 | P58: =125/5*3 -> 75 | R58: 100 | X58: =SUM(L58:W58) -> 295 | AI58: =SUM(Z58:AH58) -> 0
A59: 46024 | B59: FERNEE J CP Fernee | C59: Inward Payment | D59: 30 | F59: =F58+D59-E59 -> 22642.44 | H59: =D59-X59 -> 0 | J59: =E59-AI59 -> 0 | P59: 30 | X59: =SUM(L59:W59) -> 30 | AI59: =SUM(Z59:AH59) -> 0
A60: 46027 | B60: ANDREW PHILLIPS ANDREW PHILLIPS | C60: Inward Payment | D60: 325 | F60: =F59+D60-E60 -> 22967.44 | H60: =D60-X60 -> 0 | J60: =E60-AI60 -> 0 | O60: 200 | P60: 125 | X60: =SUM(L60:W60) -> 325 | AI60: =SUM(Z60:AH60) -> 0
A61: 46027 | B61: 800032 | C61: Cheque | E61: 40 | F61: =F60+D61-E61 -> 22927.44 | H61: =D61-X61 -> 0 | J61: =E61-AI61 -> 0 | X61: =SUM(L61:W61) -> 0 | AH61: 40 | AI61: =SUM(Z61:AH61) -> 40
A62: 46028 | B62: L+G MOSS SUBS | C62: Inward Payment | D62: 243 | F62: =F61+D62-E62 -> 23170.44 | H62: =D62-X62 -> 0 | J62: =E62-AI62 -> 0 | O62: 149.4 | P62: 93.6 | X62: =SUM(L62:W62) -> 243 | AI62: =SUM(Z62:AH62) -> 0
A63: 46034 | B63: 800033 | C63: Cheque | E63: 40 | F63: =F62+D63-E63 -> 23130.44 | H63: =D63-X63 -> 0 | J63: =E63-AI63 -> 0 | X63: =SUM(L63:W63) -> 0 | AH63: 40 | AI63: =SUM(Z63:AH63) -> 40
A64: 46038 | B64: Orsett Masonic Hall | C64: Outward Payment | E64: 2160 | F64: =F63+D64-E64 -> 20970.44 | H64: =D64-X64 -> 0 | J64: =E64-AI64 -> 0 | X64: =SUM(L64:W64) -> 0 | AD64: 2160 | AI64: =SUM(Z64:AH64) -> 2160
A65: 46041 | B65: Parkrun | C65: Outward Payment | E65: 250 | F65: =F64+D65-E65 -> 20720.44 | H65: =D65-X65 -> 0 | J65: =E65-AI65 -> 0 | X65: =SUM(L65:W65) -> 0 | AA65: 250 | AI65: =SUM(Z65:AH65) -> 250
A66: 46043 | B66: AWCOCK D LOI 20TH JAN GAVEL | C66: Inward Payment | D66: 13.06 | F66: =F65+D66-E66 -> 20733.5 | H66: =D66-X66 -> 0 | J66: =E66-AI66 -> 0 | W66: 13.06 | X66: =SUM(L66:W66) -> 13.06 | AI66: =SUM(Z66:AH66) -> 0
A67: 46050 | C67: Account Maintenance Fee | E67: 3 | F67: =F66+D67-E67 -> 20730.5 | H67: =D67-X67 -> 0 | J67: =E67-AI67 -> 0 | X67: =SUM(L67:W67) -> 0 | AG67: 3 | AI67: =SUM(Z67:AH67) -> 3
A68: 46051 | B68: 800035 | C68: Cheque | E68: 165 | F68: =F67+D68-E68 -> 20565.5 | H68: =D68-X68 -> 0 | J68: =E68-AI68 -> 0 | X68: =SUM(L68:W68) -> 0 | AA68: 165 | AI68: =SUM(Z68:AH68) -> 165
A69: 46071 | B69: Ashley Coleridge LOI | C69: Inward Payment | D69: 100 | F69: =F68+D69-E69 -> 20665.5 | H69: =D69-X69 -> 0 | J69: =E69-AI69 -> 0 | V69: 100 | X69: =SUM(L69:W69) -> 100 | AI69: =SUM(Z69:AH69) -> 0
A70: 46071 | B70: AWCOCK D LOI 17TH FEB GAVEL | C70: Inward Payment | D70: 12.22 | F70: =F69+D70-E70 -> 20677.72 | H70: =D70-X70 -> 0 | J70: =E70-AI70 -> 0 | V70: 12.22 | X70: =SUM(L70:W70) -> 12.22 | AI70: =SUM(Z70:AH70) -> 0
A71: 46078 | B71: AWCOCK D LOI 24TH FEB GAVEL | C71: Inward Payment | D71: 10 | F71: =F70+D71-E71 -> 20687.72 | H71: =D71-X71 -> 0 | J71: =E71-AI71 -> 0 | V71: 10 | X71: =SUM(L71:W71) -> 10 | AI71: =SUM(Z71:AH71) -> 0
A72: 46080 | C72: Account Maintenance Fee | E72: 3 | F72: =F71+D72-E72 -> 20684.72 | H72: =D72-X72 -> 0 | J72: =E72-AI72 -> 0 | X72: =SUM(L72:W72) -> 0 | AG72: 3 | AI72: =SUM(Z72:AH72) -> 3
A73: 46086 | B73: STEVEN PEACOCK Peacock | C73: Inward Payment | D73: 30 | F73: =F72+D73-E73 -> 20714.72 | H73: =D73-X73 -> 0 | J73: =E73-AI73 -> 0 | P73: 30 | X73: =SUM(L73:W73) -> 30 | AI73: =SUM(Z73:AH73) -> 0
A74: 46086 | B74: L+G MOSS DINNING | C74: Inward Payment | D74: 35 | F74: =F73+D74-E74 -> 20749.72 | H74: =D74-X74 -> 0 | J74: =E74-AI74 -> 0 | P74: 35 | X74: =SUM(L74:W74) -> 35 | AI74: =SUM(Z74:AH74) -> 0
A75: 46086 | B75: AWCOCK D LOFI 3RD MAR GAVEL | C75: Inward Payment | D75: 8.8 | F75: =F74+D75-E75 -> 20758.52 | H75: =D75-X75 -> 0 | J75: =E75-AI75 -> 0 | W75: 8.8 | X75: =SUM(L75:W75) -> 8.8 | AI75: =SUM(Z75:AH75) -> 0
A76: 46086 | B76: LOVELOCK PL Lovelock dining | C76: Inward Payment | D76: 30 | F76: =F75+D76-E76 -> 20788.52 | H76: =D76-X76 -> 0 | J76: =E76-AI76 -> 0 | P76: 30 | X76: =SUM(L76:W76) -> 30 | AI76: =SUM(Z76:AH76) -> 0
A77: 46087 | B77: KENNETH TURNER Dining | C77: Inward Payment | D77: 30 | F77: =F76+D77-E77 -> 20818.52 | H77: =D77-X77 -> 0 | J77: =E77-AI77 -> 0 | P77: 30 | X77: =SUM(L77:W77) -> 30 | AI77: =SUM(Z77:AH77) -> 0
A78: 46092 | B78: PHILLIP WALKER Phil Walker | C78: Inward Payment | D78: 30 | F78: =F77+D78-E78 -> 20848.52 | H78: =D78-X78 -> 0 | J78: =E78-AI78 -> 0 | P78: 30 | X78: =SUM(L78:W78) -> 30 | AI78: =SUM(Z78:AH78) -> 0
A79: 46097 | B79: Raymond Mullender LODGE DINE RAY M | C79: Inward Payment | D79: 30 | F79: =F78+D79-E79 -> 20878.52 | H79: =D79-X79 -> 0 | J79: =E79-AI79 -> 0 | P79: 30 | X79: =SUM(L79:W79) -> 30 | AI79: =SUM(Z79:AH79) -> 0
A80: 46097 | B80: STRIBLING ML M Stribling | C80: Inward Payment | D80: 30 | F80: =F79+D80-E80 -> 20908.52 | H80: =D80-X80 -> 0 | J80: =E80-AI80 -> 0 | P80: 30 | X80: =SUM(L80:W80) -> 30 | AI80: =SUM(Z80:AH80) -> 0
A81: 46097 | B81: POOLE MICHAEL Poole Dining | C81: Inward Payment | D81: 30 | F81: =F80+D81-E81 -> 20938.52 | H81: =D81-X81 -> 0 | J81: =E81-AI81 -> 0 | P81: 30 | X81: =SUM(L81:W81) -> 30 | AI81: =SUM(Z81:AH81) -> 0
A82: 46097 | B82: M Whitehead M whitehead dining | C82: Inward Payment | D82: 60 | F82: =F81+D82-E82 -> 20998.52 | H82: =D82-X82 -> 0 | J82: =E82-AI82 -> 0 | P82: 60 | X82: =SUM(L82:W82) -> 60 | AI82: =SUM(Z82:AH82) -> 0
A83: 46097 | B83: M Gillam MARK GILLAM DINE | C83: Inward Payment | D83: 30 | F83: =F82+D83-E83 -> 21028.52 | H83: =D83-X83 -> 0 | J83: =E83-AI83 -> 0 | P83: 30 | X83: =SUM(L83:W83) -> 30 | AI83: =SUM(Z83:AH83) -> 0
A84: 46098 | B84: KASTHURI R Kasthuri ( Dining) | C84: Inward Payment | D84: 30 | F84: =F83+D84-E84 -> 21058.52 | H84: =D84-X84 -> 0 | J84: =E84-AI84 -> 0 | P84: 30 | X84: =SUM(L84:W84) -> 30 | AI84: =SUM(Z84:AH84) -> 0
A85: 46098 | B85: Gavel | C85: Inward Payment | D85: 158.15 | F85: =F84+D85-E85 -> 21216.67 | H85: =D85-X85 -> 0 | J85: =E85-AI85 -> 0 | L85: 158.15 | X85: =SUM(L85:W85) -> 158.15 | AI85: =SUM(Z85:AH85) -> 0
A86: 46098 | B86: Raffle | C86: Inward Payment | D86: 220 | F86: =F85+D86-E86 -> 21436.67 | H86: =D86-X86 -> 0 | J86: =E86-AI86 -> 0 | L86: 220 | X86: =SUM(L86:W86) -> 220 | AI86: =SUM(Z86:AH86) -> 0
A87: 46098 | B87: Raffle | C87: Inward Payment | D87: 10 | F87: =F86+D87-E87 -> 21446.67 | H87: =D87-X87 -> 0 | J87: =E87-AI87 -> 0 | L87: 10 | X87: =SUM(L87:W87) -> 10 | AI87: =SUM(Z87:AH87) -> 0
A88: 46098 | B88: AFORDERBLE CATERING SLH LODGE 5217 | C88: Outward | E88: 854 | F88: =F87+D88-E88 -> 20592.67 | H88: =D88-X88 -> 0 | J88: =E88-AI88 -> 0 | X88: =SUM(L88:W88) -> 0 | AF88: 854 | AI88: =SUM(Z88:AH88) -> 854
A89: 46098 | B89: SUBs IAN JAMES | C89: Inward Payment | D89: 100 | F89: =F88+D89-E89 -> 20692.67 | H89: =D89-X89 -> 0 | J89: =E89-AI89 -> 0 | L89: 100 | X89: =SUM(L89:W89) -> 100 | AI89: =SUM(Z89:AH89) -> 0
A90: 46098 | B90: Dining minus Tyler | C90: Inward Payment | D90: 40 | F90: =F89+D90-E90 -> 20732.67 | H90: =D90-X90 -> 0 | J90: =E90-AI90 -> 0 | L90: 40 | X90: =SUM(L90:W90) -> 40 | AI90: =SUM(Z90:AH90) -> 0
F91: =F90+D91-E91 -> 20732.67 | H91: =D91-X91 -> 0 | J91: =E91-AI91 -> 0 | X91: =SUM(L91:W91) -> 0 | AI91: =SUM(Z91:AH91) -> 0
F92: =F91+D92-E92 -> 20732.67 | H92: =D92-X92 -> 0 | J92: =E92-AI92 -> 0 | X92: =SUM(L92:W92) -> 0 | AI92: =SUM(Z92:AH92) -> 0
F93: =F92+D93-E93 -> 20732.67 | H93: =D93-X93 -> 0 | J93: =E93-AI93 -> 0 | X93: =SUM(L93:W93) -> 0 | AI93: =SUM(Z93:AH93) -> 0
F94: =F93+D94-E94 -> 20732.67 | H94: =D94-X94 -> 0 | J94: =E94-AI94 -> 0 | X94: =SUM(L94:W94) -> 0 | AI94: =SUM(Z94:AH94) -> 0
F95: =F94+D95-E95 -> 20732.67 | H95: =D95-X95 -> 0 | J95: =E95-AI95 -> 0 | X95: =SUM(L95:W95) -> 0 | AI95: =SUM(Z95:AH95) -> 0
F96: =F95+D96-E96 -> 20732.67 | H96: =D96-X96 -> 0 | J96: =E96-AI96 -> 0 | X96: =SUM(L96:W96) -> 0 | AI96: =SUM(Z96:AH96) -> 0
X97: =SUM(L97:W97) -> 0 | AI97: =SUM(Z97:AH97) -> 0
A98: TOTALS | D98: =SUM(D2:D97) -> 9167.15 | E98: =SUM(E3:E97) -> 9488.2 | H98: =SUM(H2:H96) -> 0 | J98: =SUM(J2:J96) -> 0 | L98: =SUM(L2:L96) -> 1506.15 | M98: =SUM(M2:M96) -> 25 | N98: =SUM(N2:N96) -> 30 | O98: =SUM(O2:O96) -> 4269.4 | P98: =SUM(P2:P96) -> 2607.08 | Q98: =SUM(Q2:Q96) -> 30 | R98: =SUM(R2:R96) -> 100 | S98: =SUM(S2:S96) -> 0 | ... U98: =SUM(U2:U96) -> 0 | W98: =SUM(W2:W96) -> 177.3 | X98: =SUM(L98:W98) -> 8744.93 | Z98: =SUM(Z2:Z96) -> 0 | AA98: =SUM(AA2:AA96) -> 620 | AB98: =SUM(AB2:AB96) -> 2393.2 | AC98: =SUM(AC2:AC96) -> 556 | AD98: =SUM(AD2:AD96) -> 2160 | AE98: =SUM(AE2:AE96) -> 555 | AF98: =SUM(AF2:AF96) -> 3038 | AG98: =SUM(AG2:AG96) -> 6 | ... AI98: =SUM(AI2:AI96) -> 9488.2

Sheet Members
A1: Name | B1: Member Type | C1: PP Subs | D1: PP Dining | E1: Subs Due | F1: Subs Paid | G1: OWED | H1: Dining Due | I1: Dining Paid | J1: OWED | K1: Comments
A2: *Visitor
A3: Awcock,David | B3: FULL | E3: 200 | F3: 200 | G3: =E3-F3 -> 0 | H3: 125 | I3: 125 | J3: =H3-I3 -> 0
A4: Bradley Brown | B4: FULL | E4: 120 | F4: 120 | G4: =E4-F4 -> 0 | H4: 75 | I4: 75 | J4: =H4-I4 -> 0
A5: Chipperfield,David | B5: ND | E5: 200 | F5: 200 | G5: =E5-F5 -> 0 | J5: =H5-I5 -> 0
A6: Coleridge,Ashley | B6: SEC | E6: 0 | G6: =E6-F6 -> 0 | H6: 0 | J6: =H6-I6 -> 0
A7: Coleridge-Humphries,Connor | B7: ND | E7: 200 | F7: 200 | G7: =E7-F7 -> 0 | H7: 150 | I7: 150 | J7: =H7-I7 -> 0
A8: Connolly,P.J | B8: EXCLUDE | E8: 200 | G8: =E8-F8 -> 200 | J8: =H8-I8 -> 0 | K8: Spoke to his sone, he has dementia, so this money is lost
A9: Featherstone,Allen | B9: ND | E9: 200 | F9: 200 | G9: =E9-F9 -> 0 | H9: 0 | J9: =H9-I9 -> 0
A10: Fulford,Len | B10: FULL | E10: 200 | F10: 200 | G10: =E10-F10 -> 0 | H10: 125 | I10: 125 | J10: =H10-I10 -> 0
A11: Gillam,Mark | B11: PAYG | E11: 200 | F11: 200 | G11: =E11-F11 -> 0 | J11: =H11-I11 -> 0
A12: Higgins, Nicolas | B12: FULL | E12: 200 | F12: 200 | G12: =E12-F12 -> 0 | H12: 125 | I12: 125 | J12: =H12-I12 -> 0
A13: Holloway,Ian | B13: RESIGNED | E13: 200 | G13: =E13-F13 -> 200 | J13: =H13-I13 -> 0 | K13: Resigned
A14: James,Ian | B14: PAYG | E14: 400 | F14: 300 | G14: =E14-F14 -> 100 | J14: =H14-I14 -> 0
A15: Jess, Matthew | B15: FULL | E15: 200 | F15: 200 | G15: =E15-F15 -> 0 | H15: 125 | I15: 125 | J15: =H15-I15 -> 0
A16: Marshall,Arthur | B16: ND | E16: 200 | F16: 200 | G16: =E16-F16 -> 0 | J16: =H16-I16 -> 0
A17: Matondo, Herve | B17: RESIGNED | E17: 200 | G17: =E17-F17 -> 200 | J17: =H17-I17 -> 0 | K17: Resigning - write off
A18: Moss,Peter | B18: FULL | C18: 50.6 | D18: 31.4 | E18: =200-C18 -> 149.4 | F18: 149.4 | G18: =E18-F18 -> 0 | H18: =125-D18 -> 93.6 | I18: 93.6 | J18: =H18-I18 -> 0
A19: Mullender,Ray | B19: PAYG | E19: 200 | F19: 200 | G19: =E19-F19 -> 0 | J19: =H19-I19 -> 0
A20: O’Brien,Keith | B20: FULL | E20: 200 | F20: 200 | G20: =E20-F20 -> 0 | H20: 125 | I20: 125 | J20: =H20-I20 -> 0
A21: Pavey, Shaun | B21: FULL | E21: =40+200 -> 240 | G21: =E21-F21 -> 240 | J21: =H21-I21 -> 0 | K21: Reminder sent 4th Jan | L21: =G21-325 -> -85
A22: Peacock,Steve | B22: FULL | E22: 200 | F22: 200 | G22: =E22-F22 -> 0 | H22: 125 | I22: 125 | J22: =H22-I22 -> 0
A23: Petchey,Ken | B23: ND | E23: 200 | G23: =E23-F23 -> 200 | J23: =H23-I23 -> 0 | K23: Reminder sent 4th Jan
A24: Phillips,Andrew | B24: FULL | E24: 200 | F24: 200 | G24: =E24-F24 -> 0 | H24: 125 | I24: 125 | J24: =H24-I24 -> 0
A25: Porter,John | B25: RESIGNED | E25: 200 | F25: 200 | G25: =E25-F25 -> 0 | H25: 125 | I25: 125 | J25: =H25-I25 -> 0 | K25: Arrears from last year, nothing owing now
A26: South,Ray | B26: DECEASED | E26: 200 | G26: =E26-F26 -> 200 | H26: 0 | J26: =H26-I26 -> 0 | K26: Write off of course
A27: Stock,Stephen | B27: FULL | E27: 200 | F27: 200 | G27: =E27-F27 -> 0 | H27: 125 | I27: 125 | J27: =H27-I27 -> 0
A28: Stribling,Martyn | B28: ND | E28: 200 | F28: 200 | G28: =E28-F28 -> 0 | H28: 0 | J28: =H28-I28 -> 0
A29: Walden,Connor | B29: FULL | E29: 200 | F29: 200 | G29: =E29-F29 -> 0 | H29: 125 | I29: 125 | J29: =H29-I29 -> 0
A30: Walden,Mark | B30: FULL | E30: 200 | F30: 200 | G30: =E30-F30 -> 0 | H30: 125 | I30: 125 | J30: =H30-I30 -> 0
A31: Withey, Graham | B31: FULL | E31: 200 | F31: 200 | G31: =E31-F31 -> 0 | H31: 125 | I31: 125 | J31: =H31-I31 -> 0
A32: SUBSCRIBING MEMBERS | B32: =COUNTIFS(Members!B3:B31,"=FULL")+COUNTIFS(Members!B3:B31,"=ND")+COUNTIFS(Members!B3:B31,"=PAYG") -> 23 | G32: =SUM(G3:G31) -> 1340 | J32: =SUM(J3:J31) -> 0
A33: FULL Members | B33: =COUNTIFS(Members!B3:B31,"=FULL") -> 14

Sheet Dining Check
C1: Type | D1: Sep | E1: Nov | F1: Jan | G1: Mar | H1: May | I1: Total | J1: SHOULD | K1: DINED
B2: Awcock,David | C2: FULL | D2: 1 | E2: 1 | F2: 1 | G2: 1 | H2: 1 | I2: =SUM(D2:H2) -> 5 | J2: 125
B3: Awcock,Michael | C3: ND | I3: =SUM(D3:H3) -> 0 | J3: =I3*30 -> 0
B4: Bean,Peter | C4: ND | I4: =SUM(D4:H4) -> 0 | J4: =I4*30 -> 0
B5: Chipperfield,David | C5: ND | E5: 1 | G5: 1 | I5: =SUM(D5:H5) -> 2 | J5: =I5*30 -> 60
B6: Coleridge,Ashley | C6: SEC | G6: 1 | I6: =SUM(D6:H6) -> 1 | J6: =I6*30 -> 30
B7: Coleridge-Humphries,Connor | C7: ND | I7: =SUM(D7:H7) -> 0 | J7: =I7*30 -> 0
B8: Connolly,P.J | C8: ND | I8: =SUM(D8:H8) -> 0 | J8: =I8*30 -> 0
B9: Featherstone,Allen | C9: ND | I9: =SUM(D9:H9) -> 0 | J9: =I9*30 -> 0
B10: Fulford,Len | C10: FULL | D10: 1 | E10: 1 | F10: 1 | G10: 1 | H10: 1 | I10: =SUM(D10:H10) -> 5 | J10: 125
B11: Gillam,Mark | C11: PAYG | E11: 0 | F11: 0 | I11: =SUM(D11:H11) -> 0 | J11: =I11*30 -> 0
B12: Hercules-Mason,Pascoe | C12: FULL | I12: =SUM(D12:H12) -> 0 | J12: 125
B13: Higgins, Nicolas | C13: FULL | I13: =SUM(D13:H13) -> 0 | J13: 125
B14: Holloway,Ian | C14: ND | I14: =SUM(D14:H14) -> 0 | J14: =I14*30 -> 0
B15: James,Ian | C15: PAYG | D15: 1 | E15: 1 | F15: 1 | G15: 1 | H15: 1 | I15: =SUM(D15:H15) -> 5 | J15: =I15*30 -> 150
B16: Jess, Matthew | C16: FULL | I16: =SUM(D16:H16) -> 0 | J16: 125
B17: Marshall,Arthur | C17: ND | I17: =SUM(D17:H17) -> 0 | J17: =I17*30 -> 0
B18: Matondo, Herve | C18: FULL | I18: =SUM(D18:H18) -> 0 | J18: 125
B19: Moss,Peter | C19: FULL | I19: =SUM(D19:H19) -> 0 | J19: 125
B20: Mullender,Ray | C20: PAYG | G20: 1 | I20: =SUM(D20:H20) -> 1 | J20: =I20*30 -> 30
B21: O’Brien,Keith | C21: FULL | G21: 1 | I21: =SUM(D21:H21) -> 1 | J21: 125
B22: Pavey, Shaun | C22: FULL | I22: =SUM(D22:H22) -> 0 | J22: 25
B23: Peacock,Steve | C23: FULL | G23: 1 | I23: =SUM(D23:H23) -> 1 | J23: 125
B24: Petchey,Ken | C24: ND | I24: =SUM(D24:H24) -> 0 | J24: =I24*30 -> 0
B25: Phillips,Andrew | C25: FULL | I25: =SUM(D25:H25) -> 0 | J25: 125
B26: Porter,John | C26: FULL | G26: 1 | I26: =SUM(D26:H26) -> 1 | J26: 125
B27: South,Ray | C27: HON | I27: =SUM(D27:H27) -> 0 | J27: =I27*30 -> 0
B28: Stock,Stephen | C28: FULL | G28: 1 | I28: =SUM(D28:H28) -> 1 | J28: 125
B29: Stribling,Martyn | C29: ND | D29: 1 | E29: 1 | G29: 1 | H29: 1 | I29: =SUM(D29:H29) -> 4 | J29: =I29*30 -> 120
B30: Walden,Connor | C30: FULL | G30: 1 | I30: =SUM(D30:H30) -> 1 | J30: =I30*30 -> 30
B31: Walden,Mark | C31: FULL | G31: 1 | I31: =SUM(D31:H31) -> 1 | J31: 125
B32: Withey, Graham | C32: PAYG | D32: 1 | E32: 1 | G32: 1 | H32: 1 | I32: =SUM(D32:H32) -> 4 | J32: =I32*30 -> 120
B34: #Full Members-Sec @£25 | C34: =COUNTIFS(C2:C32,"FULL")-1 -> 14 | D34: 15 | E34: =$C$34 -> 14 | F34: =$C$34 -> 14 | G34: =$C$34 -> 14 | H34: 16
B35: #Visiting ND Members | D35: =SUMIFS(D2:D32,$C$2:$C$32,"ND") -> 1 | E35: =SUMIFS(E2:E32,$C$2:$C$32,"ND") -> 2 | F35: =SUMIFS(F2:F32,$C$2:$C$32,"ND") -> 0 | G35: =SUMIFS(G2:G32,$C$2:$C$32,"ND") -> 2 | H35: =SUMIFS(H2:H32,$C$2:$C$32,"ND") -> 1
B36: #Visiting PAYG Members | D36: =SUMIFS(D2:D32,$C$2:$C$32,"PAYG") -> 2 | E36: =SUMIFS(E2:E32,$C$2:$C$32,"PAYG") -> 2 | F36: =SUMIFS(F2:F32,$C$2:$C$32,"PAYG") -> 1 | G36: =SUMIFS(G2:G32,$C$2:$C$32,"PAYG") -> 3 | H36: =SUMIFS(H2:H32,$C$2:$C$32,"PAYG") -> 2
B37: Visitors | D37: 1 | E37: 5 | F37: 3 | G37: 7 | H37: 3 | I37: =SUM(D37:H37) -> 19 | J37: =I37*30 -> 570
B38: @£25 p/h always fixed-Sec | D38: =D34*25 -> 375 | E38: =E34*25 -> 350 | F38: =F34*25 -> 350 | G38: =G34*25 -> 350 | H38: =H34*25 -> 400 | I38: =SUM(D38:H38) -> 1825
B39: @£30 p/h | D39: =SUM(D35:D37)*30 -> 120 | E39: =SUM(E35:E37)*30 -> 270 | F39: =SUM(F35:F37)*30 -> 120 | G39: =SUM(G35:G37)*30 -> 360 | H39: =SUM(H35:H37)*30 -> 180 | I39: =SUM(D39:H39) -> 1050
B40: Total Fees Generated | D40: =SUM(D38:D39) -> 495 | E40: =SUM(E38:E39) -> 620 | F40: =SUM(F38:F39) -> 470 | G40: =SUM(G38:G39) -> 710 | H40: =SUM(H38:H39) -> 580 | I40: =SUM(D40:H40) -> 2875
B42: Meals Provided
B43: Members | D43: =D34 -> 15 | E43: =E34 -> 14 | F43: =F34 -> 14 | G43: =G34 -> 14 | H43: =H34 -> 16 | I43: =SUM(D43:H43) -> 73
B44: Visitors | D44: =D37 -> 1 | E44: =E37 -> 5 | F44: =F37 -> 3 | G44: =G37 -> 7 | H44: =H37 -> 3 | I44: =SUM(D44:H44) -> 19
B45: Tyler | D45: 1 | E45: 1 | F45: 1 | G45: 1 | H45: 1 | I45: =SUM(D45:H45) -> 5
B46: Secretary | D46: 1 | E46: 1 | F46: 1 | G46: 1 | H46: 1 | I46: =SUM(D46:H46) -> 5
B47: VIPS
B48: Totals | D48: =SUM(D43:D47) -> 18 | E48: =SUM(E43:E47) -> 21 | F48: =SUM(F43:F47) -> 19 | G48: =SUM(G43:G47) -> 23 | H48: =SUM(H43:H47) -> 21 | I48: =SUM(I43:I47) -> 102
B50: Costs not covered | D50: =SUM(D45:D47)*30 -> 60 | E50: =SUM(E45:E47)*30 -> 60 | F50: =SUM(F45:F47)*30 -> 60 | G50: =SUM(G45:G47)*30 -> 60 | H50: =SUM(H45:H47)*30 -> 60 | I50: =SUM(I45:I47)*30 -> 300
B52: Dining costs | D52: 700 | E52: 650 | F52: 754 | G52: 754 | H52: 546 | I52: =SUM(D52:H52) -> 3404
B53: which implies @28 p/h | D53: =INT(D52/28) -> 25 | E53: =INT(E52/28) -> 23 | F53: =INT(F52/28) -> 26 | G53: =INT(G52/28) -> 26 | H53: =INT(H52/28) -> 19
